semilattice/__init__.py
semilattice/_base_client.py
semilattice/_client.py
semilattice/_compat.py
semilattice/_constants.py
semilattice/_exceptions.py
semilattice/_files.py
semilattice/_models.py
semilattice/_qs.py
semilattice/_resource.py
semilattice/_response.py
semilattice/_streaming.py
semilattice/_types.py
semilattice/_version.py
semilattice/py.typed
semilattice/_utils/__init__.py
semilattice/_utils/_compat.py
semilattice/_utils/_datetime_parse.py
semilattice/_utils/_logs.py
semilattice/_utils/_proxy.py
semilattice/_utils/_reflection.py
semilattice/_utils/_resources_proxy.py
semilattice/_utils/_streams.py
semilattice/_utils/_sync.py
semilattice/_utils/_transform.py
semilattice/_utils/_typing.py
semilattice/_utils/_utils.py
semilattice/lib/.keep
semilattice/resources/__init__.py
semilattice/resources/answers.py
semilattice/resources/populations.py
semilattice/resources/predictions.py
semilattice/resources/tests.py
semilattice/types/__init__.py
semilattice/types/answer_benchmark_params.py
semilattice/types/answer_get_response.py
semilattice/types/answer_response.py
semilattice/types/answer_simulate_params.py
semilattice/types/api_response_list_answers.py
semilattice/types/api_response_list_populations.py
semilattice/types/api_response_list_predictions.py
semilattice/types/api_response_list_tests.py
semilattice/types/population_create_params.py
semilattice/types/population_list_params.py
semilattice/types/population_response.py
semilattice/types/prediction_batch.py
semilattice/types/prediction_create_params.py
semilattice/types/prediction_param.py
semilattice/types/prediction_response.py
semilattice/types/test_batch.py
semilattice/types/test_create_params.py
semilattice/types/test_param.py
semilattice/types/test_response.py
semilattice-0.6.0.dist-info/METADATA
semilattice-0.6.0.dist-info/WHEEL
semilattice-0.6.0.dist-info/licenses/LICENSE
semilattice-0.6.0.dist-info/RECORD
